taskcluster/__init__.py
taskcluster/auth.py
taskcluster/authevents.py
taskcluster/awsprovisioner.py
taskcluster/client.py
taskcluster/download.py
taskcluster/ec2manager.py
taskcluster/exceptions.py
taskcluster/github.py
taskcluster/githubevents.py
taskcluster/helper.py
taskcluster/hooks.py
taskcluster/hooksevents.py
taskcluster/index.py
taskcluster/login.py
taskcluster/notify.py
taskcluster/notifyevents.py
taskcluster/purgecache.py
taskcluster/queue.py
taskcluster/queueevents.py
taskcluster/retry.py
taskcluster/secrets.py
taskcluster/upload.py
taskcluster/utils.py
taskcluster/workermanager.py
taskcluster/workermanagerevents.py
taskcluster/aio/__init__.py
taskcluster/aio/asyncclient.py
taskcluster/aio/asyncutils.py
taskcluster/aio/auth.py
taskcluster/aio/authevents.py
taskcluster/aio/awsprovisioner.py
taskcluster/aio/download.py
taskcluster/aio/ec2manager.py
taskcluster/aio/github.py
taskcluster/aio/githubevents.py
taskcluster/aio/hooks.py
taskcluster/aio/hooksevents.py
taskcluster/aio/index.py
taskcluster/aio/login.py
taskcluster/aio/notify.py
taskcluster/aio/notifyevents.py
taskcluster/aio/purgecache.py
taskcluster/aio/queue.py
taskcluster/aio/queueevents.py
taskcluster/aio/reader_writer.py
taskcluster/aio/retry.py
taskcluster/aio/secrets.py
taskcluster/aio/upload.py
taskcluster/aio/workermanager.py
taskcluster/aio/workermanagerevents.py
taskcluster/generated/__init__.py
taskcluster/generated/_client_importer.py
taskcluster/generated/auth.py
taskcluster/generated/authevents.py
taskcluster/generated/github.py
taskcluster/generated/githubevents.py
taskcluster/generated/hooks.py
taskcluster/generated/hooksevents.py
taskcluster/generated/index.py
taskcluster/generated/notify.py
taskcluster/generated/notifyevents.py
taskcluster/generated/object.py
taskcluster/generated/purgecache.py
taskcluster/generated/queue.py
taskcluster/generated/queueevents.py
taskcluster/generated/secrets.py
taskcluster/generated/workermanager.py
taskcluster/generated/workermanagerevents.py
taskcluster-95.1.3.dist-info/METADATA
taskcluster-95.1.3.dist-info/WHEEL
taskcluster-95.1.3.dist-info/licenses/LICENSE
taskcluster-95.1.3.dist-info/RECORD
