Metadata-Version: 2.4
Name: taskcluster
Version: 95.1.3
Summary: Python client for Taskcluster
Project-URL: Homepage, https://github.com/taskcluster/taskcluster
Project-URL: Repository, https://github.com/taskcluster/taskcluster
Project-URL: Documentation, https://docs.taskcluster.net
Project-URL: Changelog, https://github.com/taskcluster/taskcluster/blob/main/CHANGELOG.md
Project-URL: Issues, https://github.com/taskcluster/taskcluster/issues
Author-email: Mozilla Taskcluster and Release Engineering <release+python@mozilla.com>
License: MPL-2.0
License-File: LICENSE
Keywords: api,client,taskcluster
Classifier: Intended Audience :: Developers
Classifier: License :: OSI Approved :: Mozilla Public License 2.0 (MPL 2.0)
Classifier: Programming Language :: Python :: 3
Classifier: Programming Language :: Python :: 3.9
Classifier: Programming Language :: Python :: 3.10
Classifier: Programming Language :: Python :: 3.11
Classifier: Programming Language :: Python :: 3.12
Classifier: Programming Language :: Python :: 3.13
Classifier: Programming Language :: Python :: 3.14
Classifier: Topic :: Software Development :: Libraries :: Python Modules
Requires-Python: >=3.9
Requires-Dist: aiohttp>=3.7.4
Requires-Dist: async-timeout>=2.0.0
Requires-Dist: mohawk>=0.3.4
Requires-Dist: python-dateutil>=2.8.2
Requires-Dist: requests>=2.4.3
Requires-Dist: slugid>=2
Requires-Dist: taskcluster-urls>=12.1.0
